[
  {
    "animal_id": 445553,
    "animal_subid": "AAACG1150314002",
    "animal_area_pkid": 3,
    "animal_shelter_pkid": 51,
    "animal_place": "新北市新店區公立動物之家",
    "animal_kind": "狗",
    "animal_Variety": "混種犬          ",
    "animal_sex": "F",
    "animal_bodytype": "SMALL",
    "animal_colour": "黃色",
    "animal_age": "CHILD",
    "animal_sterilization": "F",
    "animal_bacterin": "F",
    "animal_foundplace": "坪林區粗窟里金瓜寮13號",
    "animal_title": "",
    "animal_status": "OPEN",
    "animal_remark": "",
    "animal_caption": "",
    "animal_opendate": "2026-03-14",
    "animal_closeddate": "2999-12-31",
    "animal_update": "",
    "animal_createtime": "2026/03/14",
    "shelter_name": "新北市新店區公立動物之家",
    "album_file": "",
    "album_update": "",
    "cDate": "",
    "shelter_address": "新北市新店區安泰路235號",
    "shelter_tel": "02-22159462"
  },
  {
    "animal_id": 445552,
    "animal_subid": "AAACG1150314001",
    "animal_area_pkid": 3,
    "animal_shelter_pkid": 51,
    "animal_place": "新北市新店區公立動物之家",
    "animal_kind": "狗",
    "animal_Variety": "混種犬          ",
    "animal_sex": "M",
    "animal_bodytype": "BIG",
    "animal_colour": "黑色",
    "animal_age": "ADULT",
    "animal_sterilization": "T",
    "animal_bacterin": "F",
    "animal_foundplace": "新店區直潭/文學步道",
    "animal_title": "",
    "animal_status": "OPEN",
    "animal_remark": "",
    "animal_caption": "",
    "animal_opendate": "2026-03-14",
    "animal_closeddate": "2999-12-31",
    "animal_update": "",
    "animal_createtime": "2026/03/14",
    "shelter_name": "新北市新店區公立動物之家",
    "album_file": "",
    "album_update": "",
    "cDate": "",
    "shelter_address": "新北市新店區安泰路235號",
    "shelter_tel": "02-22159462"
  },
  {
    "animal_id": 436529,
    "animal_subid": "VAAAG114122601",
    "animal_area_pkid": 2,
    "animal_shelter_pkid": 49,
    "animal_place": "臺北市動物之家",
    "animal_kind": "貓",
    "animal_Variety": "混種貓                 ",
    "animal_sex": "M",
    "animal_bodytype": "SMALL",
    "animal_colour": "黑色",
    "animal_age": "ADULT",
    "animal_sterilization": "T",
    "animal_bacterin": "F",
    "animal_foundplace": "新明路",
    "animal_title": "",
    "animal_status": "OPEN",
    "animal_remark": "本動物預計於115 年1 月9 日前完成絕育手術並開放 民眾認養。",
    "animal_caption": "",
    "animal_opendate": "2026-01-02",
    "animal_closeddate": "2999-12-31",
    "animal_update": "2026/03/14",
    "animal_createtime": "2025/12/26",
    "shelter_name": "臺北市動物之家",
    "album_file": "https://www.pet.gov.tw/upload/pic/1766728851032.png",
    "album_update": "",
    "cDate": "2026/03/14",
    "shelter_address": "臺北市內湖區安美街191號",
    "shelter_tel": "02-87913254"
  },
  {
    "animal_id": 441647,
    "animal_subid": "VAAAG115020406",
    "animal_area_pkid": 2,
    "animal_shelter_pkid": 49,
    "animal_place": "臺北市動物之家",
    "animal_kind": "貓",
    "animal_Variety": "混種貓                 ",
    "animal_sex": "F",
    "animal_bodytype": "SMALL",
    "animal_colour": "虎斑色",
    "animal_age": "ADULT",
    "animal_sterilization": "T",
    "animal_bacterin": "F",
    "animal_foundplace": "大理街１６０巷２３弄",
    "animal_title": "",
    "animal_status": "OPEN",
    "animal_remark": "本動物預計於115 年2 月18 日前完成絕育手術並開放 民眾認養。",
    "animal_caption": "",
    "animal_opendate": "2026-02-11",
    "animal_closeddate": "2999-12-31",
    "animal_update": "2026/03/14",
    "animal_createtime": "2026/02/04",
    "shelter_name": "臺北市動物之家",
    "album_file": "https://www.pet.gov.tw/upload/pic/1770184598739.png",
    "album_update": "",
    "cDate": "2026/03/14",
    "shelter_address": "臺北市內湖區安美街191號",
    "shelter_tel": "02-87913254"
  },
  {
    "animal_id": 390093,
    "animal_subid": "VAAAG114011306",
    "animal_area_pkid": 2,
    "animal_shelter_pkid": 49,
    "animal_place": "臺北市動物之家",
    "animal_kind": "貓",
    "animal_Variety": "混種貓                 ",
    "animal_sex": "F",
    "animal_bodytype": "MEDIUM",
    "animal_colour": "黃虎斑色",
    "animal_age": "ADULT",
    "animal_sterilization": "F",
    "animal_bacterin": "F",
    "animal_foundplace": "八德路二段",
    "animal_title": "",
    "animal_status": "OPEN",
    "animal_remark": "右剪耳",
    "animal_caption": "",
    "animal_opendate": "2025-01-21",
    "animal_closeddate": "2999-12-31",
    "animal_update": "2026/03/14",
    "animal_createtime": "2025/01/13",
    "shelter_name": "臺北市動物之家",
    "album_file": "https://www.pet.gov.tw/upload/pic/1736753379775.png",
    "album_update": "",
    "cDate": "2026/03/14",
    "shelter_address": "臺北市內湖區安美街191號",
    "shelter_tel": "02-87913254"
  }
]